deepflow/__init__.py
deepflow/nn/__init__.py
deepflow/nn/core.py
deepflow/utils/__init__.py
deepflow/utils/run.py
deepflow/utils/utilities.py
deepflow_by_zuo-0.0.1.dist-info/LICENSE
deepflow_by_zuo-0.0.1.dist-info/METADATA
deepflow_by_zuo-0.0.1.dist-info/WHEEL
deepflow_by_zuo-0.0.1.dist-info/top_level.txt
deepflow_by_zuo-0.0.1.dist-info/RECORD
