Metadata-Version: 2.1
Name: deepflow-by-zuo
Version: 0.0.1
Summary: This is a mini but function complicated neural networks framework
Home-page: https://github.com/Coding-Zuo/MyDeep-learning-framework
Author: zuo
Author-email: zzuuoo666@sina.com
License: UNKNOWN
Platform: UNKNOWN
Classifier: Programming Language :: Python :: 3
Classifier: License :: OSI Approved :: MIT License
Classifier: Operating System :: OS Independent
Requires-Python: >=3.6
